LICENSE
MANIFEST.in
README.md
setup.py
pdcoder/__init__.py
pdcoder/main.py
pdcoder/startup_linux.sh
pdcoder/startup_win.bat
pdcoder.egg-info/PKG-INFO
pdcoder.egg-info/SOURCES.txt
pdcoder.egg-info/dependency_links.txt
pdcoder.egg-info/entry_points.txt
pdcoder.egg-info/requires.txt
pdcoder.egg-info/top_level.txt
pdcoder/__pycache__/__init__.cpython-37.pyc
pdcoder/src/__init__.py
pdcoder/src/__pycache__/__init__.cpython-37.pyc
pdcoder/src/core/CodeFormatter.py
pdcoder/src/core/Commander.py
pdcoder/src/core/MethodCall.py
pdcoder/src/core/Proxy.py
pdcoder/src/core/Statement.py
pdcoder/src/core/__init__.py
pdcoder/src/core/__pycache__/Versions.cpython-37.pyc
pdcoder/src/core/__pycache__/__init__.cpython-37.pyc
pdcoder/src/cusFuns/__init__.py
pdcoder/src/cusFuns/columnNameChanger/__init__.py
pdcoder/src/cusFuns/columnNameChanger/index.py
pdcoder/src/cusFuns/columnRemover/__init__.py
pdcoder/src/cusFuns/columnRemover/index.py
pdcoder/src/cusFuns/core/Args.py
pdcoder/src/cusFuns/core/DecoratorFuns.py
pdcoder/src/cusFuns/core/FunsPool.py
pdcoder/src/cusFuns/core/UIModl.py
pdcoder/src/cusFuns/core/__init__.py
pdcoder/src/cusFuns/core/__pycache__/Args.cpython-37.pyc
pdcoder/src/cusFuns/core/__pycache__/DecoratorFuns.cpython-37.pyc
pdcoder/src/cusFuns/core/__pycache__/FunsPool.cpython-37.pyc
pdcoder/src/cusFuns/core/__pycache__/UIModl.cpython-37.pyc
pdcoder/src/cusFuns/core/__pycache__/__init__.cpython-37.pyc
pdcoder/src/dataModel/__init__.py
pdcoder/src/dataModel/pandasCmd.py
pdcoder/src/helper/__init__.py
pdcoder/src/helper/data2model.py
pdcoder/src/helper/utils.py